stac_api_validator/__init__.py
stac_api_validator/__main__.py
stac_api_validator/filters.py
stac_api_validator/geometries.py
stac_api_validator/py.typed
stac_api_validator/validations.py
stac_api_validator-0.6.7.dist-info/LICENSE
stac_api_validator-0.6.7.dist-info/METADATA
stac_api_validator-0.6.7.dist-info/WHEEL
stac_api_validator-0.6.7.dist-info/entry_points.txt
stac_api_validator-0.6.7.dist-info/RECORD
