Metadata-Version: 2.3
Name: stac-api-validator
Version: 0.6.7
Summary: STAC API Validator
License: Apache-2.0
Author: Phil Varner
Author-email: phil@philvarner.com
Requires-Python: >=3.11,<3.14
Classifier: Development Status :: 4 - Beta
Classifier: License :: OSI Approved :: Apache Software License
Classifier: Programming Language :: Python :: 3
Classifier: Programming Language :: Python :: 3.11
Classifier: Programming Language :: Python :: 3.12
Classifier: Programming Language :: Python :: 3.13
Requires-Dist: PyYAML (>=6.0.2,<7.0.0)
Requires-Dist: Shapely (>=2.1.1)
Requires-Dist: certifi (>=2025.7.14,<2026.0.0)
Requires-Dist: click (>=8.0.2)
Requires-Dist: deepdiff (>=8.5.0,<9.0.0)
Requires-Dist: jsonschema (>=4.25.0,<5.0.0)
Requires-Dist: more_itertools (>=10.7.0,<11.0)
Requires-Dist: pystac-client (>=0.8.6,<0.10.0)
Requires-Dist: pystac[orjson] (>=1.13.0,<2.0.0)
Requires-Dist: requests (>=2.32.4,<3.0.0)
Requires-Dist: stac-check (>=1.11.1,<2.0.0)
Requires-Dist: stac-validator (>=3.10.1,<4.0.0)
Project-URL: Changelog, https://github.com/stac-utils/stac-api-validator/releases
Project-URL: Documentation, https://stac-api-validator.readthedocs.io
Project-URL: Homepage, https://github.com/stac-utils/stac-api-validator
Project-URL: Repository, https://github.com/stac-utils/stac-api-validator
